stripgpt/__init__.py
stripgpt/__main__.py
stripgpt/core.py
stripgpt-0.2.0.dist-info/licenses/LICENSE
stripgpt-0.2.0.dist-info/METADATA
stripgpt-0.2.0.dist-info/WHEEL
stripgpt-0.2.0.dist-info/entry_points.txt
stripgpt-0.2.0.dist-info/top_level.txt
stripgpt-0.2.0.dist-info/RECORD
