Metadata-Version: 2.4
Name: stripgpt
Version: 0.2.0
Summary: CLI tool to strip ChatGPT-specific markers from text
Author: Trygve Falch
License: MIT License
Project-URL: Homepage, https://example.com/stripgpt
Keywords: chatgpt,clean,cli,unicode,whitespace
Classifier: Programming Language :: Python :: 3
Classifier: Programming Language :: Python :: 3.12
Classifier: Environment :: Console
Classifier: Intended Audience :: Developers
Classifier: License :: OSI Approved :: MIT License
Requires-Python: >=3.12
License-File: LICENSE
Provides-Extra: dev
Requires-Dist: pytest>=8.0; extra == "dev"
Requires-Dist: tox>=4.0; extra == "dev"
Dynamic: license-file
